Workbook
Name \0: '[1]WAGERATE BY CRAFT'!#REF!
Name \1: #REF!
Name \a: '[1]WAGERATE BY CRAFT'!#REF!
Name \b: [2]STRSUMM0!#REF!
Name \c: "#REF!"
Name \g: #REF!
Name \k: '[3]7422CW00'!#REF!
Name \l: [4]STRSUMM0!#REF!
Name \m: #REF!
Name \MACROS: #REF!
Name \MENU: #REF!
Name \ñ: '[5]7422CW00'!#REF!
Name \q: #REF!
Name \r: #REF!
Name \t: #REF!
Name \w: #REF!
Name \z: #REF!
Name _______________f1cad: #REF!
Name _______________f1set: #REF!
Name _______________f2ango01: #REF!
Name _______________f2ango02: #REF!
Name _______________f2angora: #REF!
Name _______________f2cad: #REF!
Name _______________f2enco01: #REF!
Name _______________f2enco02: #REF!
Name _______________f2encode: #REF!
Name _______________f2glob01: #REF!
Name _______________f2global: #REF!
Name _______________f2set: #REF!
Name _______________f2set01: #REF!
Name _______________f3ang01: #REF!
Name _______________f3ang02: #REF!
Name _______________f3angora: #REF!
Name _______________f3enco01: #REF!
Name _______________f3enco02: #REF!
Name _______________f3encode: #REF!
Name _______________f3glob: #REF!
Name _______________f3glob01: #REF!
Name _______________f3set: #REF!
Name _______________f3set01: #REF!
Name _______________fac02: #REF!
Name _______________fac03: #REF!
Name _____________f1cad: #REF!
Name _____________f1set: #REF!
Name _____________f2ango01: #REF!
Name _____________f2ango02: #REF!
Name _____________f2angora: #REF!
Name _____________f2cad: #REF!
Name _____________f2enco01: #REF!
Name _____________f2enco02: #REF!
Name _____________f2encode: #REF!
Name _____________f2glob01: #REF!
Name _____________f2global: #REF!
Name _____________f2set: #REF!
Name _____________f2set01: #REF!
Name _____________f3ang01: #REF!
Name _____________f3ang02: #REF!
Name _____________f3angora: #REF!
Name _____________f3enco01: #REF!
Name _____________f3enco02: #REF!

Sheet INICIAL
C1: AMBIENTES PARA NIVEL INICIAL
C2: 0
D3: AFORO NIVEL INICIAL | E3: 0 | F3: (ALUMNOS X AULA)
R4: Para baños docentes | T4: Adicional | U4: Consolidado | V4: Baño estandar | W4: baño dis.
D5: 0 | E5: ALUMNOS DE CICLO I | G5: =ROUNDUP(D5/($E$3-5), 0) -> 0 | H5: NUM. DE AULAS CICLO I | N5: Un turno | O5: (Para la porteria) | R5: 1 | S5: Mixto 1L, 1u, 1l | T5: Mixto 1L, 1u, 1I D: 1L, 1u,1I | U5: =V5+W5 -> 8 | V5: 4 | W5: 4
D6: 0 | E6: ALUMNOS DE CICLO II | G6: =ROUNDUP(D6/$E$3, 0) -> #DIV/0! | H6: NUM. DE AULAS CICLO II | R6: 2 | S6: H 1L, 1u, 1l / M 1L, 1l | T6: H 1L, 1u, 1l / M 1L, 1l / D: 1L, 1u, 1I | U6: =V6+W6 -> 15.5 | V6: 11.5 | W6: 4
N7: =D5+D6 -> 0 | O7: (raciones) | R7: 3 | S7: H 2L, 2u, 2l / M 2L, 2l | T7: H 2L, 2u, 2l / M 2L, 2l / D: 1L, 1u, 1I | U7: =V7+W7 -> 17.5 | V7: 13.5 | W7: 4
D8: AFORO DE ADMINISTRATIVOS | R8: 4 | S8: H 3L, 3u, 3l / M 3L, 3l | T8: H 3L, 3u, 3l / M 3L, 3l / D: 1L, 1u, 1I | U8: =V8+W8 -> 21.5 | V8: 17.5 | W8: 4
D9: Subdirector | E9: =IF(SUM(G5:G6)<=9, 0, IF(SUM(G5:G6)<=20, 1, IF(SUM(G5:G6)<=40, 2, IF(SUM(G5:G6)<=60, 3, "Más de 60")))) -> #DIV/0! | R9: Leyenda: | S9: L: lavabo, u: urinario, I: inodoro
D10: Docente | E10: =SUM(N10:N11) -> #DIV/0! | N10: =G5 -> 0 | O10: Ciclo I
D11: Auxiliar | E11: =N12+N13 -> #DIV/0! | N11: =G6 -> #DIV/0! | O11: Ciclo II
D12: Secretaria | E12: =ROUNDDOWN(SUM(G5:G6)/20,0) -> #DIV/0! | N12: =ROUNDUP(G5/2,0) -> 0 | O12: Ciclo I | R12: Para baños primaria
D13: Oficinista | E13: =ROUNDUP(SUM(G5:G6)/10,0) -> #DIV/0! | N13: =ROUNDUP(G6/2,0) -> #DIV/0! | O13: Ciclo II | R13: Rango | S13: Hombres | T13: Metros | U13: Mujeres | V13: Metros | W13: Disc. (metros)
D14: Personal de Servicio | E14: =ROUNDUP(SUM(G5:G6)/8,0) -> #DIV/0! | R14: 1 | S14: H: 1L, 1u, 1I | T14: 6.5 | U14: M: 1L, 1I | V14: 6.5 | W14: 4
D15: Porteria | E15: =IF(N5="Un turno", 1, IF(N5="Ambos turnos", 2, "")) -> 1 | R15: 2 | S15: H: 2L, 2u, 2I | T15: 8.5 | U15: M: 2L, 2I | V15: 9 | W15: 4
R16: 3 | S16: H: 3L, 3u, 3I | T16: 10.5 | U16: M: 3L, 3I | V16: 11.5 | W16: 4
R17: 4 | S17: H: 4L, 4u, 4I | T17: 12.5 | U17: M: 4L, 4I | V17: 14 | W17: 4
C18: PROGRAMA ARQUITECTONICO INICIAL | R18: 5 | S18: H: 5L, 5u, 5I | T18: 14.5 | U18: M: 5L, 5I | V18: 16.5 | W18: 4
R19: 6 | S19: H: 6L, 6u, 6I | T19: 16.5 | U19: M: 6L, 6I | V19: 19 | W19: 4
B20: USO | D20: AMBIENTE | G20: Ambiente | H20: Ocupación | I20: Util. unitaria | J20: Parcial | R20: Leyenda: | S20: L: lavabo, u: urinario, I: inodoro
B21: AMBIENTES BASICO | C21: A | D21: Aula
E22: Aulas de Ciclo I | G22: 20 | H22: 2 | I22: =G22*H22 -> 40 | J22: =I22*G5 -> 0
E23: Aulas de Ciclo II | G23: 25 | H23: 2.4 | I23: =G23*H23 -> 60 | J23: =I23*G6 -> #DIV/0!
E24: SS HH | I24: 37.5 | J24: =I24 -> 37.5
E25: Deposito* | I25: 9 | J25: =I25*(SUM(G5:G6)/2) -> #DIV/0!
D26: Aula de Psicomotricidad | J26: =IF(SUM(G5:G6)<6, 0, IF(SUM(G5:G6)<16, 1, IF(SUM(G5:G6)<26, 2, 3))) -> #DIV/0!
E27: Menos de 6 aulas = 0, en el SUM | J27: =IF(SUM(G5:G6)<6, 0, IF(SUM(G5:G6)<16, 1, IF(SUM(G5:G6)<26, 2, 3)))*50 -> #DIV/0!
E28: 6 a 15 aulas= 1 | G28: 25 | H28: 2 | I28: =G28*H28 -> 50
E29: 16 a 25 aulas= 2 | G29: 25 | H29: 2 | I29: =G29*H29 -> 50
E30: 26 a 35 aulas= 3 | G30: 25 | H30: 2 | I30: =G30*H30 -> 50
C31: D | D31: Sala de Usos Multiples SUM
E32: SUM | G32: 30 a más | H32: 1 | I32: 120 | J32: =I32 -> 120
E33: Deposito | H33: 10% del SUM | I33: =I32*10% -> 12 | J33: =I33 -> 12
C34: F | D34: Area de Ingreso | H34: 0.4 | I34: =H34*SUM(D5:D6) -> 0 | J34: =I34 -> 0
D35: Circulaciones, según propuesta | I35: variable
D36: Espacios exteriores
E37: Patio | H37: 1.5 | I37: =H37*SUM(D5:D6) -> 0 | J37: =I37 -> 0
E38: Area de juegos | H38: 1 | I38: =H38*SUM(D5:D6) -> 0 | J38: =I38 -> 0
C39: G | D39: Espacio de cultivos | H39: mínimo | I39: 13 | J39: =I39 -> 13
D40: Espacios de crianza de animales | I40: variable
B41: AMBIENTES COMPLEMENTARIOS | C41: Gestión administrativa y pedagógica | D41: Area de Espera | G41: 1 | H41: 5 | I41: =G41*H41 -> 5 | J41: =I41 -> 5
D42: Espacio personal administrativo | G42: =SUM(E12:E13) -> #DIV/0! | H42: 3.25 | I42: =G42*H42 -> #DIV/0! | J42: =I42 -> #DIV/0!
D43: Sala de Reuniones | G43: =E10+E11 -> #DIV/0! | H43: 1.5 | I43: =MAX(H43 * G43, 12) -> #DIV/0! | J43: =I43 -> #DIV/0!
D44: Sala para personal docente | G44: =E10 -> #DIV/0! | H44: 1.5 | I44: =G44*H44+10 -> #DIV/0! | J44: =I44 -> #DIV/0!
C45: Bienestar estudiantil | D45: Topico | I45: 9 | J45: =I45 -> 9
D46: Lactario | I46: 7.5 | J46: =I46 -> 7.5
D47: Cocina
E48: Tipo A | G48: Hasta 150 raciones | H48: 10
E49: Tipo B | H49: 11.3
E50: Tipo C | G50: 151 a 300 | H50: 13.5 | I50: =IF(N7/2<151,"Tipo A",IF(AND(N7/2>150,N7/2<301),"Tipo C",IF(AND(N7/2>300,N7/2<901),"Tipo D",IF(AND(N7/2>900),"Tipo E",0)))) -> Tipo A | J50: =VLOOKUP(I50,E48:H52,4,FALSE) -> 10
E51: Tipo D | G51: 301 a 900 | H51: 24.3
E52: Tipo E | G52: 901 a más | H52: 32.3
D53: Almacen de alimentos
E54: Tipo A | G54: Tipo I | H54: 4.2
E55: Tipo B | G55: Tipo II | H55: 4.2
E56: Tipo C | G56: Tipo III | H56: 6 | I56: =I50 -> Tipo A | J56: =VLOOKUP(I56,E54:H58,4,FALSE) -> 4.2
E57: Tipo D | G57: Tipo IV | H57: 9
E58: Tipo E | G58: Tipo V | H58: 10.3
D59: Deposito de combustible | H59: 3 | J59: =H59 -> 3
D60: Comedor (compartido con el SUM) | H60: variable | I60: =((N7/3)*1.5) -> 0 | J60: =I60 -> 0
C61: Servicios generales | D61: Almacen | H61: minimo 10 | I61: =1.5*SUM(G5:G6) -> #DIV/0! | J61: =I61 -> #DIV/0!
D62: Caseta de control | H62: minimo 3 | I62: 3 | J62: =I62 -> 3
D63: Cuarto de maquinas y cisternas | H63: según diseño
D64: Ambiente para almacenamiento de residuo solido | H64: variable
D65: Cuarto electrico | H65: variable
D66: Cuarto de limpieza | H66: minimo 1.5 | I66: 1.5 | J66: =I66 -> 1.5
D67: Estacionamientos | H67: variable
C68: Servicios higienicos | D68: Servicios Higienicos administrativos, pedagogicos
D69: De 1 a 6 empleados: Mixto 1L, 1u, 1l
D70: De 7 a 20 empleados: H 1L, 1u, 1l / M 1L, 1l | G70: =IF(SUM(E9:E15)<=6,1,IF(SUM(E9:E15)<=20,2,IF(SUM(E9:E15)<=60,3,IF(SUM(E9:E15)<=150,4,"Fuera de rango")))) -> #DIV/0! | H70: =VLOOKUP(G70,R5:S8,2,FALSE) -> #DIV/0! | I70: =VLOOKUP(H70,S5:T8,2,FALSE) -> #DIV/0! | J70: =VLOOKUP(I70,T5:U8,2,FALSE) -> #DIV/0!
D71: De 21 a 60 empleados: H 2L, 2u, 2l / M 2L, 2l
D72: De 61 a 150 empleados: H 3L, 3u, 3l / M 3L, 3l
D73: Servicios Higienicos personal de cocina
D74: De 1 a 5 empleados: MIXTO 1L, 1u, 1l | H74: =S5 -> Mixto 1L, 1u, 1l | J74: =VLOOKUP(H74,S5:V8,4,FALSE) -> 4
D75: Servicios Higienicos para alumnos
E76: Hombres | H76: =_xlfn.CONCAT("H: ", ROUNDUP(SUM(D5:D6)/2/25, 0), "L, ", ROUNDUP(SUM(D5:D6)/2/25, 0), "u, ", ROUNDUP(SUM(D5:D6)/2/25, 0), "I") -> H: 0L, 0u, 0I | I76: =VLOOKUP(H76,S14:T19,2,FALSE) -> #N/A | J76: =I76 -> #N/A
E77: Mujeres | H77: =_xlfn.CONCAT("M: ", ROUNDUP(SUM(D5:D6)/2/25, 0), "L, ", ROUNDUP(SUM(D5:D6)/2/25, 0), "I") -> M: 0L, 0I | I77: =VLOOKUP(H77,U14:V19,2,FALSE) -> #N/A | J77: =I77 -> #N/A
E78: Disc. | H78: D: 1L, 1u,1I | I78: =W14 -> 4 | J78: =I78 -> 4

Sheet PRIM
C1: AMBIENTES PARA NIVEL PRIMARIO
D3: AFORO NIVEL PRIMARIO | E3: 40 | F3: (ALUMNOS X AULA)
R4: Para baños docentes | T4: Adicional | U4: Consolidado | V4: Baño estandar | W4: baño dis.
D5: 40 | E5: ALUMNOS DE 1 RO | G5: =ROUNDUP(D5/$E$3, 0) -> 1 | H5: NUM. DE AULAS DE 1RO | N5: Un turno | O5: (Para la porteria) | R5: 1 | S5: Mixto 1L, 1u, 1l | T5: Mixto 1L, 1u, 1I D: 1L, 1u,1I | U5: =V5+W5 -> 8 | V5: 4 | W5: 4
D6: 40 | E6: ALUMNOS DE 2DO | G6: =ROUNDUP(D6/$E$3, 0) -> 1 | H6: NUM. DE AULAS DE 2DO | R6: 2 | S6: H 1L, 1u, 1l / M 1L, 1l | T6: H 1L, 1u, 1l / M 1L, 1l / D: 1L, 1u, 1I | U6: =V6+W6 -> 15.5 | V6: 11.5 | W6: 4
D7: 40 | E7: ALUMNOS DE 3RO | G7: =ROUNDUP(D7/$E$3, 0) -> 1 | H7: NUM. DE AULAS DE 3RO
D8: 40 | E8: ALUMNOS DE 4TO | G8: =ROUNDUP(D8/$E$3, 0) -> 1 | H8: NUM. DE AULAS DE 4TO
D9: 40 | E9: ALUMNOS DE 5TO | G9: =ROUNDUP(D9/$E$3, 0) -> 1 | H9: NUM. DE AULAS DE 5TO
D10: 40 | E10: ALUMNOS DE 6TO | G10: =ROUNDUP(D10/$E$3, 0) -> 1 | H10: NUM. DE AULAS DE 6TO
N11: =SUM(D5:D10) -> 240 | O11: (raciones) | R11: 3 | S11: H 2L, 2u, 2l / M 2L, 2l | T11: H 2L, 2u, 2l / M 2L, 2l / D: 1L, 1u, 1I | U11: =V11+W11 -> 17.5 | V11: 13.5 | W11: 4
D12: AFORO DE ADMINISTRATIVOS | R12: 4 | S12: H 3L, 3u, 3l / M 3L, 3l | T12: H 3L, 3u, 3l / M 3L, 3l / D: 1L, 1u, 1I | U12: =V12+W12 -> 21.5 | V12: 17.5 | W12: 4
D13: Subdirector | E13: =IF(SUM(G5:G10)<=9, 0, IF(SUM(G5:G10)<=20, 1, IF(SUM(G5:G10)<=40, 2, IF(SUM(G5:G10)<=60, 3, "Más de 60")))) -> 0 | R13: Leyenda: | S13: L: lavabo, u: urinario, I: inodoro
D14: Docente | E14: =SUM(G5:G10) -> 6
D15: Educ. fisica | E15: =ROUNDDOWN(SUM(G5:G10)/10,0) -> 0
D16: Profesor IP | E16: =E3/E3 -> 1
D17: Secretaria | E17: =MIN(ROUNDDOWN(SUM(G5:G10)/20,0),1) -> 0 | R17: Para baños primaria
D18: Oficinista | E18: =ROUNDDOWN(SUM(G5:G10)/10,0) -> 0 | R18: Rango | S18: Hombres | T18: Metros | U18: Mujeres | V18: Metros | W18: Disc. (metros)
D19: Personal de Servicio | E19: =ROUNDUP(SUM(G5:G10)/8,0) -> 1 | R19: 1 | S19: H: 1L, 1u, 1I | T19: 6.5 | U19: M: 1L, 1I | V19: 6.5 | W19: 4
D20: Porteria | E20: =IF(N5="Un turno", 1, IF(N5="Ambos turnos", 2, "")) -> 1 | R20: 2 | S20: H: 2L, 2u, 2I | T20: 8.5 | U20: M: 2L, 2I | V20: 9 | W20: 4
D21: Aux. biblioteca | E21: =ROUNDDOWN(SUM(G5:G10)/10,0) -> 0
R22: 3 | S22: H: 3L, 3u, 3I | T22: 10.5 | U22: M: 3L, 3I | V22: 11.5 | W22: 4
R23: 4 | S23: H: 4L, 4u, 4I | T23: 12.5 | U23: M: 4L, 4I | V23: 14 | W23: 4
C24: PROGRAMA ARQUITECTONICO PRIMARIA | R24: 5 | S24: H: 5L, 5u, 5I | T24: 14.5 | U24: M: 5L, 5I | V24: 16.5 | W24: 4
R25: 6 | S25: H: 6L, 6u, 6I | T25: 16.5 | U25: M: 6L, 6I | V25: 19 | W25: 4
B26: USO | D26: AMBIENTE | G26: Ambiente | H26: Ocupación | I26: Util. unitaria | J26: Parcial | R26: 7 | S26: H: 7L, 7u, 7I | T26: 19.5 | U26: M: 7L, 7I | V26: 21 | W26: 4
B27: AMBIENTES BASICO | C27: A | D27: Aula | R27: Leyenda: | S27: L: lavabo, u: urinario, I: inodoro
D28: (incorpora mobiliaria para material didactico permanente) | G28: =E3 -> 40 | H28: 2 | I28: =G28*H28 -> 80
E29: 1er Grado | F29: =G5 -> 1 | J29: =F29*$I$28 -> 80
E30: 2do Grado | F30: =G6 -> 1 | J30: =F30*$I$28 -> 80
E31: 3er Grado | F31: =G7 -> 1 | J31: =F31*$I$28 -> 80
E32: 4to Grado | F32: =G8 -> 1 | J32: =F32*$I$28 -> 80
E33: 5to Grado | F33: =G9 -> 1 | J33: =F33*$I$28 -> 80
E34: 6to Grado | F34: =G10 -> 1 | J34: =F34*$I$28 -> 80
C35: B | D35: Biblioteca Escolar
E36: Tipo I | F36: hasta 30 secc | G36: 30 | H36: 2.5 | I36: =G36*H36+25%*G36*H36 -> 93.75
E37: Tipo II | F37: de 31 a 48 secc | G37: 45 | H37: 2 | I37: =G37*H37+25%*G37*H37 -> 112.5 | J37: =VLOOKUP((IF(SUM(G5:G10)<=30, "hasta 30 secc", IF(AND(SUM(G5:G10)>=31, SUM(G5:G10)<=48), "de 31 a 48 secc", IF(SUM(G5:G10)>=49, "Más de 49 secc", "")))),F36:I38,4,FALSE) -> 93.75
E38: Tipo III | F38: mas de 49 secc | G38: 60 | H38: 2 | I38: =G38*H38+25%*G38*H38 -> 150
D39: Aula de Innovacion Pedagogica AIP
E40: hasta 15 = | F40: 1 | G40: 30 | H40: 3 | I40: =G40*H40 -> 90
E41: De 16 a 30 = | F41: 2 | G41: 30 | H41: 3 | I41: =G41*H41 -> 90
E42: De 31 a 45 = | F42: 3 | G42: 30 | H42: 3 | I42: =G42*H42 -> 90 | J42: =VLOOKUP(IF(SUM(G5:G10)<=15,"hasta 15 =",IF(SUM(G5:G10)<=30,"De 16 a 30 =",IF(SUM(G5:G10)<=45,"De 31 a 45 =","De 46 a mas ="))),E40:F43,2,FALSE)*I40 -> 90
E43: De 46 a mas = | F43: 4 | G43: 30 | H43: 3 | I43: =G43*H43 -> 90
E44: Modulo de conectividad, anexo al AIP | I44: 25.8 | J44: =I44 -> 25.8
C45: C | D45: Taller Creativo
E46: hasta 15 = | F46: 1 | G46: 30 | H46: 3 | I46: =G46*H46 -> 90
E47: De 16 a 30 = | F47: 2 | G47: 30 | H47: 3 | I47: =G47*H47 -> 90
E48: De 31 a 45 = | F48: 3 | G48: 30 | H48: 3 | I48: =G48*H48 -> 90 | J48: =VLOOKUP(IF(SUM(G5:G10)<=15,"hasta 15 =",IF(SUM(G5:G10)<=30,"De 16 a 30 =",IF(SUM(G5:G10)<=45,"De 31 a 45 =","De 46 a mas ="))),E46:F49,2,FALSE)*I46 -> 90
E49: De 46 a mas = | F49: 4 | G49: 30 | H49: 3 | I49: =G49*H49 -> 90
C50: D | D50: Sala de Usos Multiples SUM
E51: SUM | G51: 30 a más | H51: 1 | I51: =IF(SUM(G5:G10)<4,90,IF(SUM(G5:G10)<10,150,300)) -> 150 | J51: =I51 -> 150
E52: Deposito | H52: 15% del SUM | I52: =I51*15% -> 22.5 | J52: =I52 -> 22.5
C53: F | D53: Losa Multiuso | H53: según propuesta
D54: Area de Ingreso | H54: variable | J54: 50
D55: Circulaciones, según propuesta | H55: variable
D56: Area libre
E57: Tipo I | F57: 0.3 | G57: terreno
E58: Tipo II | F58: 0.4 | G58: terreno
E59: Tipo III | F59: 0.6 | G59: terreno
C60: G | D60: Espacio de cultivos | H60: mínimo | I60: 15 | J60: =I60 -> 15
D61: Espacios de crianza de animales | I61: variable
B62: AMBIENTES COMPLEMENTARIOS | C62: Gestión administrativa y pedagógica | D62: Area de Espera | G62: 1 | H62: 5 | I62: =G62*H62 -> 5 | J62: =I62 -> 5
D63: Espacio personal administrativo | G63: =IF(SUM(E17:E18)=0,1,SUM(E17:E18)) -> 1 | H63: 3.25 | I63: =G63*H63 -> 3.25 | J63: =I63 -> 3.25
D64: Sala de Reuniones | G64: =E14 -> 6 | H64: 1.5 | I64: =MAX(H64 * G64, 12) -> 12 | J64: =I64 -> 12
D65: Sala para personal docente | J65: =IF(SUM(G5:G10)<=30,"Tipo I:","Tipo II:") -> Tipo I:
E66: Tipo I: | F66: hasta 30 secc | G66: =IF(J65=E66,SUM(G5:G10),0) -> 6 | H66: 1.5 | I66: =G66*H66 -> 9 | J66: =I66 -> 9
E67: Tipo II: | F67: mas de 30 secc | G67: =IF(J65=E67,SUM(G5:G10),0) -> 0 | H67: 1.5 | I67: =G67*H67 -> 0 | J67: =I67 -> 0
C68: Bienestar estudiantil | D68: Topico | I68: 9 | J68: =I68 -> 9
D69: Lactario | I69: 7.5 | J69: =I69 -> 7.5
D70: Cocina
E71: Tipo A | G71: Hasta 150 raciones | H71: 10
E72: Tipo B | H72: 11.3
E73: Tipo C | G73: 151 a 300 | H73: 13.5 | I73: =IF(N11/2<151,"Tipo A",IF(AND(N11/2>150,N11/2<301),"Tipo C",IF(AND(N11/2>300,N11/2<901),"Tipo D",IF(AND(N11/2>900),"Tipo E",0)))) -> Tipo A | J73: =VLOOKUP(I73,E71:H75,4,FALSE) -> 10
E74: Tipo D | G74: 301 a 900 | H74: 24.3
E75: Tipo E | G75: 901 a más | H75: 32.3
D76: Almacen de alimentos
E77: Tipo A | G77: Tipo I | H77: 4.2
E78: Tipo B | G78: Tipo II | H78: 4.2
E79: Tipo C | G79: Tipo III | H79: 6 | I79: =I73 -> Tipo A | J79: =VLOOKUP(I79,E77:H81,4,FALSE) -> 4.2
E80: Tipo D | G80: Tipo IV | H80: 9
E81: Tipo E | G81: Tipo V | H81: 10.3
D82: Deposito de combustible | H82: 3 | J82: =H82 -> 3
D83: Comedor (compartido con el SUM) | H83: variable | I83: =((N11/3)*1.5) -> 120 | J83: =I83 -> 120
C84: Servicios generales | D84: Almacen | H84: minimo 10 | I84: =1.5*SUM(G5:G6) -> 3 | J84: =I84 -> 3
D85: Caseta de control | H85: minimo 3 | I85: 3 | J85: =I85 -> 3
D86: Cuarto de maquinas y cisternas | H86: según diseño
D87: Ambiente para almacenamiento de residuo solido | H87: variable
D88: Cuarto electrico | H88: variable
D89: Cuarto de limpieza | H89: minimo 1.5 | I89: 1.5 | J89: =I89 -> 1.5
D90: Estacionamientos | H90: variable
C91: Servicios higienicos | D91: Servicios Higienicos administrativos, pedagogicos
D92: De 1 a 6 empleados: Mixto 1L, 1u, 1l
D93: De 7 a 20 empleados: H 1L, 1u, 1l / M 1L, 1l | G93: =IF(SUM(E13:E20)<=6,1,IF(SUM(E13:E20)<=20,2,IF(SUM(E13:E20)<=60,3,IF(SUM(E13:E20)<=150,4,"Fuera de rango")))) -> 2 | H93: =VLOOKUP(G93,R5:S12,2,FALSE) -> H 1L, 1u, 1l / M 1L, 1l | I93: =VLOOKUP(H93,S5:T12,2,FALSE) -> H 1L, 1u, 1l / M 1L, 1l / D: 1L, 1u, 1I | J93: =VLOOKUP(I93,T5:U12,2,FALSE) -> 15.5
D94: De 21 a 60 empleados: H 2L, 2u, 2l / M 2L, 2l
D95: De 61 a 150 empleados: H 3L, 3u, 3l / M 3L, 3l
D96: Servicios Higienicos personal de cocina
D97: De 1 a 5 empleados: MIXTO 1L, 1u, 1l | H97: =S5 -> Mixto 1L, 1u, 1l | J97: =VLOOKUP(H97,S5:V12,4,FALSE) -> 4
D98: Servicios Higienicos para alumnos
E99: Hombres | H99: =_xlfn.CONCAT("H: ", ROUNDUP(SUM(D5:D10)/2/25, 0), "L, ", ROUNDUP(SUM(D5:D10)/2/25, 0), "u, ", ROUNDUP(SUM(D5:D10)/2/25, 0), "I") -> H: 5L, 5u, 5I | I99: =VLOOKUP(H99,S19:T26,2,FALSE) -> 14.5 | J99: =I99 -> 14.5
E100: Mujeres | H100: =_xlfn.CONCAT("M: ", ROUNDUP(SUM(D5:D10)/2/25, 0), "L, ", ROUNDUP(SUM(D5:D10)/2/25, 0), "I") -> M: 5L, 5I | I100: =VLOOKUP(H100,U19:V26,2,FALSE) -> 16.5 | J100: =I100 -> 16.5
E101: Disc. | H101: D: 1L, 1u,1I | I101: =W19 -> 4 | J101: =I101 -> 4

Sheet SEC
C1: AMBIENTES PARA NIVEL SECUNDARIO
D3: AFORO NIVEL SECUNDARIO | E3: 20 | F3: (ALUMNOS X AULA)
R4: Para baños docentes | T4: Adicional | U4: Consolidado | V4: Baño estandar | W4: baño dis.
D5: 20 | E5: ALUMNOS DE 1 RO | G5: =ROUNDUP(D5/$E$3, 0) -> 1 | H5: NUM. DE AULAS DE 1RO | N5: Un turno | O5: (Para la porteria) | R5: 1 | S5: Mixto 1L, 1u, 1l | T5: Mixto 1L, 1u, 1I D: 1L, 1u,1I | U5: =V5+W5 -> 8 | V5: 4 | W5: 4
D6: 20 | E6: ALUMNOS DE 2DO | G6: =ROUNDUP(D6/$E$3, 0) -> 1 | H6: NUM. DE AULAS DE 2DO | R6: 2 | S6: H 1L, 1u, 1l / M 1L, 1l | T6: H 1L, 1u, 1l / M 1L, 1l / D: 1L, 1u, 1I | U6: =V6+W6 -> 15.5 | V6: 11.5 | W6: 4
D7: 20 | E7: ALUMNOS DE 3RO | G7: =ROUNDUP(D7/$E$3, 0) -> 1 | H7: NUM. DE AULAS DE 3RO
D8: 20 | E8: ALUMNOS DE 4TO | G8: =ROUNDUP(D8/$E$3, 0) -> 1 | H8: NUM. DE AULAS DE 4TO
D9: 20 | E9: ALUMNOS DE 5TO | G9: =ROUNDUP(D9/$E$3, 0) -> 1 | H9: NUM. DE AULAS DE 5TO
N10: =SUM(D5:D9) -> 100 | O10: (raciones) | R10: 3 | S10: H 2L, 2u, 2l / M 2L, 2l | T10: H 2L, 2u, 2l / M 2L, 2l / D: 1L, 1u, 1I | U10: =V10+W10 -> 17.5 | V10: 13.5 | W10: 4
D11: AFORO DE ADMINISTRATIVOS | R11: 4 | S11: H 3L, 3u, 3l / M 3L, 3l | T11: H 3L, 3u, 3l / M 3L, 3l / D: 1L, 1u, 1I | U11: =V11+W11 -> 21.5 | V11: 17.5 | W11: 4
D12: Subdirector | E12: =IF(SUM(G5:G9)<=9, 0, IF(SUM(G5:G9)<=20, 1, IF(SUM(G5:G9)<=40, 2, IF(SUM(G5:G9)<=60, 3, "Más de 60")))) -> 0 | R12: Leyenda: | S12: L: lavabo, u: urinario, I: inodoro
D13: Docente | E13: =SUM(G5:G9) -> 5
D14: Educ. fisica | E14: =ROUNDDOWN(SUM(G5:G9)/10,0) -> 0
D15: Profesor IP | E15: =E3/E3 -> 1
D16: Coordi. de tutoria | E16: =ROUNDDOWN(SUM(G5:G9)/15,0) -> 0
D17: Coordi. Pedagogico | E17: =ROUNDDOWN(SUM(G6:G10)/15,0) -> 0
D18: Auxiliar | E18: =ROUNDDOWN(SUM(G7:G11)/8,0) -> 0
D19: Jefe de Laboratorio | E19: =ROUNDDOWN(SUM(G7:G11)/20,0) -> 0
D20: Aux, Laboratorio | E20: =IF(SUM(G5:G9)>15,1,0) -> 0
D21: Secretaria | E21: =MIN(ROUNDDOWN(SUM(G5:G9)/20,0),1) -> 0
D22: Oficinista | E22: =ROUNDDOWN(SUM(G5:G9)/10,0) -> 0 | R22: Para baños primaria
D23: Personal de Servicio | E23: =ROUNDUP(SUM(G5:G9)/8,0) -> 1 | R23: Rango | S23: Hombres | T23: Metros | U23: Mujeres | V23: Metros | W23: Disc. (metros)
D24: Porteria | E24: =IF(N5="Un turno", 1, IF(N5="Ambos turnos", 2, "")) -> 1 | R24: 1 | S24: H: 1L, 1u, 1I | T24: 6.5 | U24: M: 1L, 1I | V24: 6.5 | W24: 4
D25: Psicologo | E25: 1 | R25: 2 | S25: H: 2L, 2u, 2I | T25: 8.5 | U25: M: 2L, 2I | V25: 9 | W25: 4
D26: Aux. biblioteca | E26: =ROUNDDOWN(SUM(G5:G9)/10,0) -> 0
R27: 3 | S27: H: 3L, 3u, 3I | T27: 10.5 | U27: M: 3L, 3I | V27: 11.5 | W27: 4
R28: 4 | S28: H: 4L, 4u, 4I | T28: 12.5 | U28: M: 4L, 4I | V28: 14 | W28: 4
C29: PROGRAMA ARQUITECTONICO PRIMARIA | R29: 5 | S29: H: 5L, 5u, 5I | T29: 14.5 | U29: M: 5L, 5I | V29: 16.5 | W29: 4
R30: 6 | S30: H: 6L, 6u, 6I | T30: 16.5 | U30: M: 6L, 6I | V30: 19 | W30: 4
B31: USO | D31: AMBIENTE | G31: Ambiente | H31: Ocupación | I31: Util. unitaria | J31: Parcial | R31: Leyenda: | S31: L: lavabo, u: urinario, I: inodoro
B32: AMBIENTES BASICO | C32: A | D32: Aula
D33: (incorpora mobiliaria para material didactico permanente) | G33: =E3 -> 20 | H33: 2 | I33: =G33*H33 -> 40
E34: 1er Grado | F34: =G5 -> 1 | J34: =F34*$I$33 -> 40
E35: 2do Grado | F35: =G6 -> 1 | J35: =F35*$I$33 -> 40
E36: 3er Grado | F36: =G7 -> 1 | J36: =F36*$I$33 -> 40
E37: 4to Grado | F37: =G8 -> 1 | J37: =F37*$I$33 -> 40
E38: 5to Grado | F38: =G9 -> 1 | J38: =F38*$I$33 -> 40
C39: B | D39: Biblioteca Escolar
E40: Tipo I | F40: hasta 30 secc | G40: 30 | H40: 2.5 | I40: =G40*H40+25%*G40*H40 -> 93.75
E41: Tipo II | F41: de 31 a 48 secc | G41: 45 | H41: 2 | I41: =G41*H41+25%*G41*H41 -> 112.5 | J41: =VLOOKUP((IF(SUM(G5:G9)<=30, "hasta 30 secc", IF(AND(SUM(G5:G9)>=31, SUM(G5:G9)<=48), "de 31 a 48 secc", IF(SUM(G5:G9)>=49, "Más de 49 secc", "")))),F40:I42,4,FALSE) -> 93.75
E42: Tipo III | F42: mas de 49 secc | G42: 60 | H42: 2 | I42: =G42*H42+25%*G42*H42 -> 150
D43: Aula de Innovacion Pedagogica AIP
E44: hasta 8 = | F44: 1 | G44: 30 | H44: 3 | I44: =G44*H44 -> 90
E45: De 9 a 17 = | F45: 2 | G45: 30 | H45: 3 | I45: =G45*H45 -> 90
E46: De 18 a 26 = | F46: 3 | G46: 30 | H46: 3 | I46: =G46*H46 -> 90
E47: De 27 a 35 = | F47: 4 | G47: 30 | H47: 3 | I47: =G47*H47 -> 90 | J47: =VLOOKUP(IF(SUM(G5:G9)<=8,"hasta 8 =",IF(SUM(G5:G9)<=17,"De 9 a 17 =",IF(SUM(G5:G9)<=26,"De 18 a 26 =",IF(SUM(G5:G9)<=35,"De 27 a 35 =",IF(SUM(G5:G9)<=43,"De 36 a 43 =",IF(SUM(G5:G9)<=52,"De 44 a 52 =","De 53 a 66 =")))))),E44:F50,2,FALSE)*I44 -> 90
E48: De 36 a 43 = | F48: 5 | G48: 30 | H48: 3 | I48: =G48*H48 -> 90
E49: De 44 a 52 = | F49: 6 | G49: 30 | H49: 3 | I49: =G49*H49 -> 90
E50: De 53 a 66 = | F50: 7 | G50: 30 | H50: 3 | I50: =G50*H50 -> 90
E51: Modulo de conectividad, anexo al AIP | I51: 25.8 | J51: =I51 -> 25.8
C52: C | D52: Taller Creativo
E53: hasta 10 = | F53: 1 | G53: 30 | H53: 3 | I53: =G53*H53 -> 90
E54: De 11 a 20 = | F54: 2 | G54: 30 | H54: 3 | I54: =G54*H54 -> 90
E55: De 21 a 30 = | F55: 3 | G55: 30 | H55: 3 | I55: =G55*H55 -> 90 | J55: =VLOOKUP(IF(SUM(G5:G9)<=10,"hasta 10 =",IF(SUM(G5:G9)<=20,"De 11 a 20 =",IF(SUM(G5:G9)<=30,"De 21 a 30 =",IF(SUM(G5:G9)<=40,"De 31 a 40 =",IF(SUM(G5:G9)<=50,"De 41 a 50 =","De 51 a 60 ="))))),E53:F58,2,FALSE)*I53 -> 90
E56: De 31 a 40 = | F56: 4 | G56: 30 | H56: 3 | I56: =G56*H56 -> 90
E57: De 41 a 50 = | F57: 5 | G57: 30 | H57: 3 | I57: =G57*H57 -> 90
E58: De 51 a 60 = | F58: 6 | G58: 30 | H58: 3 | I58: =G58*H58 -> 90
D59: Taller de Educacion para el Trabajo
E60: De 1 a 15 = | F60: 1 | G60: 30 | H60: 3 | I60: =G60*H60 -> 90
E61: De 16 a 30 = | F61: 2 | G61: 30 | H61: 3 | I61: =G61*H61 -> 90
E62: De 31 a 45 = | F62: 3 | G62: 30 | H62: 3 | I62: =G62*H62 -> 90 | J62: =VLOOKUP(IF(SUM(G5:G9)<=15,"De 1 a 15 =",IF(SUM(G5:G9)<=30,"De 16 a 30 =",IF(SUM(G5:G9)<=45,"De 31 a 45 =",IF(SUM(G5:G9)<=60,"De 46 a 60 =")))),E60:F63,2,FALSE)*I60 -> 90
E63: De 46 a 60 = | F63: 4 | G63: 30 | H63: 3 | I63: =G63*H63 -> 90
D64: Laboratorio de Ciencia,Tecnología y Ambiente
E65: De 1 a 15 = | F65: 1 | G65: 30 | H65: 3 | I65: =G65*H65 -> 90
E66: De 16 a 30 = | F66: 2 | G66: 30 | H66: 3 | I66: =G66*H66 -> 90
E67: De 31 a 45 = | F67: 3 | G67: 30 | H67: 3 | I67: =G67*H67 -> 90 | J67: =VLOOKUP(IF(SUM(G5:G9)<=15,"De 1 a 15 =",IF(SUM(G5:G9)<=30,"De 16 a 30 =",IF(SUM(G5:G9)<=45,"De 31 a 45 =",IF(SUM(G5:G9)<=60,"De 46 a 60 =")))),E65:F68,2,FALSE)*I65 -> 90
E68: De 46 a 60 = | F68: 4 | G68: 30 | H68: 3 | I68: =G68*H68 -> 90
C69: D | D69: Sala de Usos Multiples SUM
E70: SUM | G70: 30 a más | H70: 1 | I70: =IF(SUM(G5:G9)<4,90,IF(SUM(G5:G9)<10,150,300)) -> 150 | J70: =I70 -> 150
E71: Deposito | H71: 15% del SUM | I71: =I70*15% -> 22.5 | J71: =I71 -> 22.5
C72: F | D72: Losa Multiuso | H72: según propuesta
D73: Area de Ingreso | H73: variable | J73: 50
D74: Circulaciones, según propuesta | H74: variable
D75: Area libre
E76: Tipo I | F76: 0.3 | G76: terreno
E77: Tipo II | F77: 0.4 | G77: terreno
E78: Tipo III | F78: 0.6 | G78: terreno
C79: G | D79: Espacio de cultivos | H79: mínimo | I79: 15 | J79: =I79 -> 15
D80: Espacios de crianza de animales | I80: variable
B81: AMBIENTES COMPLEMENTARIOS | C81: Gestión administrativa y pedagógica | D81: Area de Espera | G81: 1 | H81: 5 | I81: =G81*H81 -> 5 | J81: =I81 -> 5
D82: Espacio personal administrativo | G82: =IF(SUM(E21:E22)=0,1,(SUM(E21:E22))) -> 1 | H82: 3.25 | I82: =G82*H82 -> 3.25 | J82: =I82 -> 3.25
D83: Sala de Reuniones | G83: =E13 -> 5 | H83: 1.5 | I83: =MAX(H83 * G83, 12) -> 12 | J83: =I83 -> 12
D84: Sala para personal docente | J84: =IF(SUM(G5:G9)<=15,"Tipo I:","Tipo II:") -> Tipo I:
E85: Tipo I: | F85: hasta 15 secc | G85: =IF(J84=E85,SUM(G5:G9),0) -> 5 | H85: 1.5 | I85: =G85*H85 -> 7.5 | J85: =I85 -> 7.5
E86: Tipo II: | F86: mas de 15 secc | G86: =IF(J84=E86,SUM(G5:G9),0) -> 0 | H86: 1.5 | I86: =G86*H86 -> 0 | J86: =I86 -> 0
C87: Bienestar estudiantil | D87: Topico | I87: 9 | J87: =I87 -> 9
D88: Lactario | I88: 7.5 | J88: =I88 -> 7.5
D89: Cocina
E90: Tipo A | G90: Hasta 150 raciones | H90: 10
E91: Tipo B | H91: 11.3
E92: Tipo C | G92: 151 a 300 | H92: 13.5 | I92: =IF(N10/2<151,"Tipo A",IF(AND(N10/2>150,N10/2<301),"Tipo C",IF(AND(N10/2>300,N10/2<901),"Tipo D",IF(AND(N10/2>900),"Tipo E",0)))) -> Tipo A | J92: =VLOOKUP(I92,E90:H94,4,FALSE) -> 10
E93: Tipo D | G93: 301 a 900 | H93: 24.3
E94: Tipo E | G94: 901 a más | H94: 32.3
D95: Almacen de alimentos
E96: Tipo A | G96: Tipo I | H96: 4.2
E97: Tipo B | G97: Tipo II | H97: 4.2
E98: Tipo C | G98: Tipo III | H98: 6 | I98: =I92 -> Tipo A | J98: =VLOOKUP(I98,E96:H100,4,FALSE) -> 4.2
E99: Tipo D | G99: Tipo IV | H99: 9
E100: Tipo E | G100: Tipo V | H100: 10.3
D101: Deposito de combustible | H101: 3 | J101: =H101 -> 3
...

Sheet UNIFICADO
C2: CONSOLIDADO TOTAL PARA EL PROYECTO
C4: Ambientes | D4: Metros cuadrados | E4: Cantidad | F4: Unitario
C5: Aulas Ciclo I | D5: =INICIAL!J22 -> 0 | E5: =INICIAL!G5 -> 0 | F5: =IFERROR(D5/E5, 0) -> 0
B6: Aulas Inicial | C6: Aulas Ciclo II | D6: =INICIAL!J23 -> #DIV/0! | E6: =INICIAL!G6 -> #DIV/0! | F6: =IFERROR(D6/E6, 0) -> 0
C7: Aulas Psicomotricidad | D7: =INICIAL!J27 -> #DIV/0! | E7: =D7/INICIAL!I28 -> #DIV/0! | F7: =IFERROR(D7/E7, 0) -> 0
C8: Aulas Primaria | D8: =SUM(PRIM!J29:J34) -> 480 | E8: =SUM(PRIM!G5:G10) -> 6 | F8: =D8/E8 -> 80
C9: Aulas Secundaria | D9: =SUM(SEC!J34:J38) -> 200 | E9: =SUM(SEC!G5:G9) -> 5 | F9: =D9/E9 -> 40
C10: Biblioteca | D10: =SEC!J41 -> 93.75 | E10: 1 | F10: =D10/E10 -> 93.75
C11: Aula de Innovacion Prim | D11: =PRIM!J42 -> 90 | E11: =D11/90 -> 1 | F11: =D11/E11 -> 90
C12: Aula de Innovacion Sec | D12: =SEC!J47 -> 90 | E12: =D12/90 -> 1 | F12: =D12/E12 -> 90
C13: Taller creativo Prim | D13: =PRIM!J48 -> 90 | E13: =D13/90 -> 1 | F13: =D13/E13 -> 90
C14: Taller creativo Sec | D14: =SEC!J55 -> 90 | E14: =D14/90 -> 1 | F14: =D14/E14 -> 90
C15: Taller EPT | D15: =SEC!J62 -> 90 | E15: =D15/SEC!I60 -> 1 | F15: =D15/E15 -> 90
C16: Laboratorio | D16: =SEC!J67 -> 90 | E16: =D16/SEC!J67 -> 1 | F16: =D16/E16 -> 90
C17: SUM | D17: =MAX(INICIAL!J32,PRIM!J51,SEC!J70)+MAX(INICIAL!J33,PRIM!J52,SEC!J71) -> 172.5 | E17: 1 | F17: =D17/E17 -> 172.5
C18: Direccion Adm. | D18: =INICIAL!J42+PRIM!J63+SEC!J82 -> #DIV/0! | E18: 1 | F18: =D18/E18 -> #DIV/0!
C19: Área de espera | D19: =INICIAL!J41*3 -> 15 | E19: 1 | F19: =D19/E19 -> 15
C20: Sala de Reuniones | D20: =INICIAL!J43+PRIM!J64+SEC!J83 -> #DIV/0! | E20: 1 | F20: =D20/E20 -> #DIV/0!
C21: Sala de Profesores | D21: =INICIAL!J44+SUM(PRIM!J66:J67)+SUM(SEC!J85:J86) -> #DIV/0! | E21: 1 | F21: =D21/E21 -> #DIV/0!
C22: SSHH Adm. | D22: =INICIAL!J70+PRIM!J93+SEC!J112 -> #DIV/0! | E22: 1 | F22: =D22/E22 -> #DIV/0!
C23: Cocina Prim - Sec | D23: =PRIM!J73+SEC!J92+PRIM!J79+SEC!J98 +PRIM!J97+SEC!J116 -> 36.4 | E23: 1 | F23: =D23/E23 -> 36.4
C24: Cocina Inicial | D24: =INICIAL!J50+INICIAL!J56+INICIAL!J74 -> 18.2 | E24: 1 | F24: =D24/E24 -> 18.2
C25: SSHH Inicial | D25: =IFERROR(SUM(INICIAL!J76:J78),0) -> 0 | E25: 1 | F25: =IFERROR(D25/E25,0) -> 0
C26: SSHH Prim | D26: =SUM(PRIM!J99:J101) -> 35 | E26: 1 | F26: =D26/E26 -> 35
C27: SSHH Sec | D27: =SUM(SEC!J118:J120) -> 21.5 | E27: 1 | F27: =D27/E27 -> 21.5
C28: Losa Deportiva | D28: 840 | E28: 1 | F28: =D28/E28 -> 840
C29: Topico | D29: =SEC!J87*3 -> 27 | E29: 1 | F29: =D29/E29 -> 27
C30: Lactario | D30: =SEC!J88*3 -> 22.5 | E30: 1 | F30: =D30/E30 -> 22.5
C31: Escalera Prim | D31: 37.5 | E31: 2 | F31: 18.75
C32: Escalera Sec | D32: 37.5 | E32: 2 | F32: 18.75
C33: Patio de Inicial | D33: 150 | E33: 1 | F33: 150
C34: Area de ingreso | D34: 18 | E34: 1 | F34: 18
C35: Total | F35: =SUM(D5:D34) -> #DIV/0!

Sheet CALCULOS
A1: Ambientes | B1: Metros cuadrados | C1: Cantidad | D1: Unitario | E1: Ancho | F1: Largo | G1: Tipo | H1: Pabellon | I1: Piso de preferencia
A2: Aulas Secundaria | B2: =VLOOKUP(A2,UNIFICADO!$C$5:$F$34,2,FALSE) -> 200 | C2: =VLOOKUP(A2,UNIFICADO!$C$5:$F$34,3,FALSE) -> 5 | D2: =VLOOKUP(A2,UNIFICADO!$C$5:$F$34,4,FALSE) -> 40 | E2: 7.5 | F2: =D2/E2 -> 5.3333333 | G2: Fijo | H2: Derecha | I2: 1 y 2 | J2: Distribuir en una sola hilera. Prioridad máxima del pabellón.
A3: Aula de Innovacion Sec | B3: =VLOOKUP(A3,UNIFICADO!$C$5:$F$34,2,FALSE) -> 90 | C3: =VLOOKUP(A3,UNIFICADO!$C$5:$F$34,3,FALSE) -> 1 | D3: =VLOOKUP(A3,UNIFICADO!$C$5:$F$34,4,FALSE) -> 90 | E3: 7.5 | F3: =D3/E3 -> 12 | G3: Fijo | H3: Derecha | I3: 1 y 2 | J3: Ubicar preferentemente en 1er piso; usar 2do solo si no hay espacio.
A4: Taller creativo Sec | B4: =VLOOKUP(A4,UNIFICADO!$C$5:$F$34,2,FALSE) -> 90 | C4: =VLOOKUP(A4,UNIFICADO!$C$5:$F$34,3,FALSE) -> 1 | D4: =VLOOKUP(A4,UNIFICADO!$C$5:$F$34,4,FALSE) -> 90 | E4: 7.5 | F4: =D4/E4 -> 12 | G4: Fijo | H4: Derecha | I4: 1 y 2 | J4: Ubicar preferentemente en 1er piso; usar 2do solo si no hay espacio.
A5: Laboratorio | B5: =VLOOKUP(A5,UNIFICADO!$C$5:$F$34,2,FALSE) -> 90 | C5: =VLOOKUP(A5,UNIFICADO!$C$5:$F$34,3,FALSE) -> 1 | D5: =VLOOKUP(A5,UNIFICADO!$C$5:$F$34,4,FALSE) -> 90 | E5: 7.5 | F5: =D5/E5 -> 12 | G5: Fijo | H5: Derecha | I5: 1 | J5: Solo en primer piso por seguridad y equipamiento.
A6: Escalera Sec | B6: =VLOOKUP(A6,UNIFICADO!$C$5:$F$34,2,FALSE) -> 37.5 | C6: =VLOOKUP(A6,UNIFICADO!$C$5:$F$34,3,FALSE) -> 2 | D6: =VLOOKUP(A6,UNIFICADO!$C$5:$F$34,4,FALSE) -> 18.75 | E6: 7.5 | F6: 2.5 | G6: Fijo | H6: Derecha | I6: 1 y 2 | J6: Considerar largo suficiente para alto flujo de estudiantes.
A7: SSHH Sec | B7: =VLOOKUP(A7,UNIFICADO!$C$5:$F$34,2,FALSE) -> 21.5 | C7: =VLOOKUP(A7,UNIFICADO!$C$5:$F$34,3,FALSE) -> 1 | D7: =VLOOKUP(A7,UNIFICADO!$C$5:$F$34,4,FALSE) -> 21.5 | E7: 7.5 | F7: =D7/E7 -> 2.8666667 | G7: Variable | H7: Derecha | I7: 1 | J7: Ubicar en extremos del pabellón, alejados de aulas.
A8: Aulas Primaria | B8: =VLOOKUP(A8,UNIFICADO!$C$5:$F$34,2,FALSE) -> 480 | C8: =VLOOKUP(A8,UNIFICADO!$C$5:$F$34,3,FALSE) -> 6 | D8: =VLOOKUP(A8,UNIFICADO!$C$5:$F$34,4,FALSE) -> 80 | E8: 7.5 | F8: =D8/E8 -> 10.666667 | G8: Fijo | H8: Izquierda | I8: 1 y 2 | J8: Distribuir en una sola hilera. Prioridad máxima del pabellón.
A9: Biblioteca | B9: =VLOOKUP(A9,UNIFICADO!$C$5:$F$34,2,FALSE) -> 93.75 | C9: =VLOOKUP(A9,UNIFICADO!$C$5:$F$34,3,FALSE) -> 1 | D9: =VLOOKUP(A9,UNIFICADO!$C$5:$F$34,4,FALSE) -> 93.75 | E9: 7.5 | F9: =D9/E9 -> 12.5 | G9: Fijo | H9: Izquierda | I9: 1 | J9: Solo en primer piso por seguridad y equipamiento.
A10: Aula de Innovacion Prim | B10: =VLOOKUP(A10,UNIFICADO!$C$5:$F$34,2,FALSE) -> 90 | C10: =VLOOKUP(A10,UNIFICADO!$C$5:$F$34,3,FALSE) -> 1 | D10: =VLOOKUP(A10,UNIFICADO!$C$5:$F$34,4,FALSE) -> 90 | E10: 7.5 | F10: =D10/E10 -> 12 | G10: Fijo | H10: Izquierda | I10: 1 y 2 | J10: Ubicar preferentemente en 1er piso; usar 2do solo si no hay espacio.
A11: Taller creativo Prim | B11: =VLOOKUP(A11,UNIFICADO!$C$5:$F$34,2,FALSE) -> 90 | C11: =VLOOKUP(A11,UNIFICADO!$C$5:$F$34,3,FALSE) -> 1 | D11: =VLOOKUP(A11,UNIFICADO!$C$5:$F$34,4,FALSE) -> 90 | E11: 7.5 | F11: =D11/E11 -> 12 | G11: Fijo | H11: Izquierda | I11: 1 y 2 | J11: Ubicar preferentemente en 1er piso; usar 2do solo si no hay espacio.
A12: Escalera Prim | B12: =VLOOKUP(A12,UNIFICADO!$C$5:$F$34,2,FALSE) -> 37.5 | C12: =VLOOKUP(A12,UNIFICADO!$C$5:$F$34,3,FALSE) -> 2 | D12: =VLOOKUP(A12,UNIFICADO!$C$5:$F$34,4,FALSE) -> 18.75 | E12: 7.5 | F12: 2.5 | G12: Fijo | H12: Izquierda | I12: 1 y 2 | J12: Considerar largo suficiente para alto flujo de estudiantes.
A13: SSHH Prim | B13: =VLOOKUP(A13,UNIFICADO!$C$5:$F$34,2,FALSE) -> 35 | C13: =VLOOKUP(A13,UNIFICADO!$C$5:$F$34,3,FALSE) -> 1 | D13: =VLOOKUP(A13,UNIFICADO!$C$5:$F$34,4,FALSE) -> 35 | E13: 7.5 | F13: =D13/E13 -> 4.6666667 | G13: Variable | H13: Izquierda | I13: 1 | J13: Ubicar en extremos del pabellón, alejados de aulas.
A14: Aulas Ciclo I | B14: =VLOOKUP(A14,UNIFICADO!$C$5:$F$34,2,FALSE) -> 0 | C14: =VLOOKUP(A14,UNIFICADO!$C$5:$F$34,3,FALSE) -> 0 | D14: =VLOOKUP(A14,UNIFICADO!$C$5:$F$34,4,FALSE) -> 0 | E14: =D14/F14 -> 0 | F14: 7.5 | G14: Fijo | H14: Inferior | I14: 1 | J14: Distribuir en una sola hilera. Prioridad máxima del pabellón. Solo primer piso. El pabellon debe estar aislado de los otros pabellones.
A15: Aulas Ciclo II | B15: =VLOOKUP(A15,UNIFICADO!$C$5:$F$34,2,FALSE) -> #DIV/0! | C15: =VLOOKUP(A15,UNIFICADO!$C$5:$F$34,3,FALSE) -> #DIV/0! | D15: =VLOOKUP(A15,UNIFICADO!$C$5:$F$34,4,FALSE) -> 0 | E15: =D15/F15 -> 0 | F15: 7.5 | G15: Fijo | H15: Inferior | I15: 1 y 2 | J15: Distribuir en una sola hilera. Máximo segundo piso.
A16: Aulas Psicomotricidad | B16: =VLOOKUP(A16,UNIFICADO!$C$5:$F$34,2,FALSE) -> #DIV/0! | C16: =VLOOKUP(A16,UNIFICADO!$C$5:$F$34,3,FALSE) -> #DIV/0! | D16: =VLOOKUP(A16,UNIFICADO!$C$5:$F$34,4,FALSE) -> 0 | E16: =D16/F16 -> 0 | F16: 7.5 | G16: Fijo | H16: Inferior | I16: 1 | J16: Ubicar siempre junto a aulas. No deben alejarse del conjunto principal.
A17: Topico | B17: =VLOOKUP(A17,UNIFICADO!$C$5:$F$34,2,FALSE) -> 27 | C17: =VLOOKUP(A17,UNIFICADO!$C$5:$F$34,3,FALSE) -> 1 | D17: =VLOOKUP(A17,UNIFICADO!$C$5:$F$34,4,FALSE) -> 27 | E17: =D17/F17 -> 3.6 | F17: 7.5 | G17: Fijo | H17: Inferior | I17: 1 | J17: Ubicar al lado del lactario y en un extremo del pabellón.
A18: Lactario | B18: =VLOOKUP(A18,UNIFICADO!$C$5:$F$34,2,FALSE) -> 22.5 | C18: =VLOOKUP(A18,UNIFICADO!$C$5:$F$34,3,FALSE) -> 1 | D18: =VLOOKUP(A18,UNIFICADO!$C$5:$F$34,4,FALSE) -> 22.5 | E18: =D18/F18 -> 3 | F18: 7.5 | G18: Fijo | H18: Inferior | I18: 1 | J18: Ubicar al lado del topico y en un extremo del pabellón.
A19: SSHH Inicial | B19: =VLOOKUP(A19,UNIFICADO!$C$5:$F$34,2,FALSE) -> 0 | C19: =VLOOKUP(A19,UNIFICADO!$C$5:$F$34,3,FALSE) -> 1 | D19: =VLOOKUP(A19,UNIFICADO!$C$5:$F$34,4,FALSE) -> 0 | E19: =D19/F19 -> 0 | F19: 7.5 | G19: Variable | H19: Inferior | I19: 1 | J19: Ubicar en un extremo del pabellón. Acceso directo desde áreas de aulas.
A20: Cocina Inicial | B20: =VLOOKUP(A20,UNIFICADO!$C$5:$F$34,2,FALSE) -> 18.2 | C20: =VLOOKUP(A20,UNIFICADO!$C$5:$F$34,3,FALSE) -> 1 | D20: =VLOOKUP(A20,UNIFICADO!$C$5:$F$34,4,FALSE) -> 18.2 | E20: =D20/F20 -> 2.4266667 | F20: 7.5 | G20: Variable | H20: Inferior | I20: 1 | J20: Ubicar alejada de las aulas por seguridad, ruido y olores.
A21: Direccion Adm. | B21: =VLOOKUP(A21,UNIFICADO!$C$5:$F$34,2,FALSE) -> #DIV/0! | C21: =VLOOKUP(A21,UNIFICADO!$C$5:$F$34,3,FALSE) -> 1 | D21: =VLOOKUP(A21,UNIFICADO!$C$5:$F$34,4,FALSE) -> #DIV/0! | E21: =D21/F21 -> #DIV/0! | F21: 5 | G21: Variable | H21: Superior | I21: 1 | J21: Al lado del área de ingreso.
A22: Área de espera | B22: =VLOOKUP(A22,UNIFICADO!$C$5:$F$34,2,FALSE) -> 15 | C22: =VLOOKUP(A22,UNIFICADO!$C$5:$F$34,3,FALSE) -> 1 | D22: =VLOOKUP(A22,UNIFICADO!$C$5:$F$34,4,FALSE) -> 15 | E22: =D22/F22 -> 3 | F22: 5 | G22: Variable | H22: Superior | I22: 1 | J22: Cercano a la dirección
A23: Sala de Reuniones | B23: =VLOOKUP(A23,UNIFICADO!$C$5:$F$34,2,FALSE) -> #DIV/0! | C23: =VLOOKUP(A23,UNIFICADO!$C$5:$F$34,3,FALSE) -> 1 | D23: =VLOOKUP(A23,UNIFICADO!$C$5:$F$34,4,FALSE) -> #DIV/0! | E23: =D23/F23 -> #DIV/0! | F23: 5 | G23: Variable | H23: Superior | I23: 1 | J23: Cercano a la dirección
A24: Area de ingreso | B24: =VLOOKUP(A24,UNIFICADO!$C$5:$F$34,2,FALSE) -> 18 | C24: =VLOOKUP(A24,UNIFICADO!$C$5:$F$34,3,FALSE) -> 1 | D24: =VLOOKUP(A24,UNIFICADO!$C$5:$F$34,4,FALSE) -> 18 | E24: =D24/F24 -> 3.6 | F24: 5 | G24: Fijo | H24: Superior | I24: 1 | J24: Al centro del pabellon, debe ser el punto de ingreso para todo el colegio.
A25: Sala de Profesores | B25: =VLOOKUP(A25,UNIFICADO!$C$5:$F$34,2,FALSE) -> #DIV/0! | C25: =VLOOKUP(A25,UNIFICADO!$C$5:$F$34,3,FALSE) -> 1 | D25: =VLOOKUP(A25,UNIFICADO!$C$5:$F$34,4,FALSE) -> #DIV/0! | E25: =D25/F25 -> #DIV/0! | F25: 5 | G25: Variable | H25: Superior | I25: 1 | J25: Zona de descanso, debe ser tranquilo, evitar cercania a las aulas de los otros pabellones
A26: SSHH Adm. | B26: =VLOOKUP(A26,UNIFICADO!$C$5:$F$34,2,FALSE) -> #DIV/0! | C26: =VLOOKUP(A26,UNIFICADO!$C$5:$F$34,3,FALSE) -> 1 | D26: =VLOOKUP(A26,UNIFICADO!$C$5:$F$34,4,FALSE) -> #DIV/0! | E26: =D26/F26 -> #DIV/0! | F26: 5 | G26: Variable | H26: Superior | I26: 1 | J26: Ubicar en un extremo del pabellón. Acceso directo desde áreas de aulas.
A27: Losa Deportiva | B27: =VLOOKUP(A27,UNIFICADO!$C$5:$F$34,2,FALSE) -> 840 | C27: =VLOOKUP(A27,UNIFICADO!$C$5:$F$34,3,FALSE) -> 1 | D27: =VLOOKUP(A27,UNIFICADO!$C$5:$F$34,4,FALSE) -> 840 | E27: 15 | F27: 28 | G27: Fijo | H27: Medio | I27: 1 | J27: Se orienta de norte a sur siempre. Se siguen las medidas que se especifican, además si el terreno lo permite debe distribuirse otra cancha con al menos 3 metros de separación de la otra.
A28: Taller EPT | B28: =VLOOKUP(A28,UNIFICADO!$C$5:$F$34,2,FALSE) -> 90 | C28: =VLOOKUP(A28,UNIFICADO!$C$5:$F$34,3,FALSE) -> 1 | D28: =VLOOKUP(A28,UNIFICADO!$C$5:$F$34,4,FALSE) -> 90 | E28: 7.5 | F28: =D28/E28 -> 12 | G28: Fijo | H28: Medio | I28: 1 | J28: Más cercano a secundaria, pero alejado de inicial
A29: SUM | B29: =VLOOKUP(A29,UNIFICADO!$C$5:$F$34,2,FALSE) -> 172.5 | C29: =VLOOKUP(A29,UNIFICADO!$C$5:$F$34,3,FALSE) -> 1 | D29: =VLOOKUP(A29,UNIFICADO!$C$5:$F$34,4,FALSE) -> 172.5 | E29: 16 | F29: =D29/E29 -> 10.78125 | G29: Fijo | H29: Medio | I29: 1 | J29: Debe ubicarse al medio de la distribucion
A30: Cocina Prim - Sec | B30: =VLOOKUP(A30,UNIFICADO!$C$5:$F$34,2,FALSE) -> 36.4 | C30: =VLOOKUP(A30,UNIFICADO!$C$5:$F$34,3,FALSE) -> 1 | D30: =VLOOKUP(A30,UNIFICADO!$C$5:$F$34,4,FALSE) -> 36.4 | E30: 7.5 | F30: =D30/E30 -> 4.8533333 | G30: Variable | H30: Medio | I30: 1 | J30: De preferencia estar cerca al SUM
A31: Patio de Inicial | B31: =VLOOKUP(A31,UNIFICADO!$C$5:$F$34,2,FALSE) -> 150 | C31: =VLOOKUP(A31,UNIFICADO!$C$5:$F$34,3,FALSE) -> 1 | D31: =VLOOKUP(A31,UNIFICADO!$C$5:$F$34,4,FALSE) -> 150 | E31: 7.5 | F31: =D31/E31 -> 20 | G31: Variable | H31: Medio | I31: 1 | J31: Estar cerca al pabellon inicial, para efectos de cercania. No tiene dimensiones definidas.

Sheet COSTOS EXCEL
A1: ITEM | B1: MODULO | C1: CANTIDAD | D1: UND | E1: AREA UTIL (norma técnica) | F1: AREA UTIL +30% DE CIRCULACION Y MUROS | G1: ÁREA POR MODULO | H1: COSTO | I1: COSTO PARCIAL | J1: COSTO MODULO
A2: 1 | B2: MODULO I | G2: =SUM(F3:F7) -> #DIV/0! | J2: =SUM(I3:I7) -> #DIV/0!
A3: 1.1 | B3: Aulas Ciclo I | C3: =VLOOKUP(B3,UNIFICADO!$C$5:$F$34,3,FALSE) -> 0 | D3: M2 | E3: =VLOOKUP(B3,UNIFICADO!$C$5:$F$34,2,FALSE) -> 0 | F3: =E3+30%*E3 -> 0 | H3: 1084.5763 | I3: =F3*H3 -> 0
A4: 1.2 | B4: Aulas Ciclo II | C4: =VLOOKUP(B4,UNIFICADO!$C$5:$F$34,3,FALSE) -> #DIV/0! | D4: M2 | E4: =VLOOKUP(B4,UNIFICADO!$C$5:$F$34,2,FALSE) -> #DIV/0! | F4: =E4+30%*E4 -> #DIV/0! | H4: 1084.5763 | I4: =F4*H4 -> #DIV/0!
A5: 1.3 | B5: Aulas Psicomotricidad | C5: =VLOOKUP(B5,UNIFICADO!$C$5:$F$34,3,FALSE) -> #DIV/0! | D5: M2 | E5: =VLOOKUP(B5,UNIFICADO!$C$5:$F$34,2,FALSE) -> #DIV/0! | F5: =E5+30%*E5 -> #DIV/0! | H5: 1084.5763 | I5: =F5*H5 -> #DIV/0!
A6: 1.4 | B6: Aulas Primaria | C6: =VLOOKUP(B6,UNIFICADO!$C$5:$F$34,3,FALSE) -> 6 | D6: M2 | E6: =VLOOKUP(B6,UNIFICADO!$C$5:$F$34,2,FALSE) -> 480 | F6: =E6+30%*E6 -> 624 | H6: 1084.5763 | I6: =F6*H6 -> 676775.59
A7: 1.5 | B7: Aulas Secundaria | C7: =VLOOKUP(B7,UNIFICADO!$C$5:$F$34,3,FALSE) -> 5 | D7: M2 | E7: =VLOOKUP(B7,UNIFICADO!$C$5:$F$34,2,FALSE) -> 200 | F7: =E7+30%*E7 -> 260 | H7: 1084.5763 | I7: =F7*H7 -> 281989.83
A8: 2 | B8: MODULO II | G8: =SUM(F9:F19) -> #DIV/0! | J8: =SUM(I9:I19) -> #DIV/0!
A9: 2.1 | B9: Direccion Adm. | C9: =VLOOKUP(B9,UNIFICADO!$C$5:$F$34,3,FALSE) -> 1 | D9: M2 | E9: =VLOOKUP(B9,UNIFICADO!$C$5:$F$34,2,FALSE) -> #DIV/0! | F9: =E9+30%*E9 -> #DIV/0! | H9: 1084.5763 | I9: =F9*H9 -> #DIV/0!
A10: 2.2 | B10: Sala de Reuniones | C10: =VLOOKUP(B10,UNIFICADO!$C$5:$F$34,3,FALSE) -> 1 | D10: M2 | E10: =VLOOKUP(B10,UNIFICADO!$C$5:$F$34,2,FALSE) -> #DIV/0! | F10: =E10+30%*E10 -> #DIV/0! | H10: 1084.5763 | I10: =F10*H10 -> #DIV/0!
A11: 2.3 | B11: Sala de Profesores | C11: =VLOOKUP(B11,UNIFICADO!$C$5:$F$34,3,FALSE) -> 1 | D11: M2 | E11: =VLOOKUP(B11,UNIFICADO!$C$5:$F$34,2,FALSE) -> #DIV/0! | F11: =E11+30%*E11 -> #DIV/0! | H11: 1084.5763 | I11: =F11*H11 -> #DIV/0!
A12: 2.4 | B12: Biblioteca | C12: =VLOOKUP(B12,UNIFICADO!$C$5:$F$34,3,FALSE) -> 1 | D12: M2 | E12: =VLOOKUP(B12,UNIFICADO!$C$5:$F$34,2,FALSE) -> 93.75 | F12: =E12+30%*E12 -> 121.875 | H12: 1084.5763 | I12: =F12*H12 -> 132182.73
A13: 2.5 | B13: Aula de Innovacion Prim | C13: =VLOOKUP(B13,UNIFICADO!$C$5:$F$34,3,FALSE) -> 1 | D13: M2 | E13: =VLOOKUP(B13,UNIFICADO!$C$5:$F$34,2,FALSE) -> 90 | F13: =E13+30%*E13 -> 117 | H13: 1084.5763 | I13: =F13*H13 -> 126895.42
A14: 2.6 | B14: Aula de Innovacion Sec | C14: =VLOOKUP(B14,UNIFICADO!$C$5:$F$34,3,FALSE) -> 1 | D14: M2 | E14: =VLOOKUP(B14,UNIFICADO!$C$5:$F$34,2,FALSE) -> 90 | F14: =E14+30%*E14 -> 117 | H14: 1084.5763 | I14: =F14*H14 -> 126895.42
A15: 2.7 | B15: Taller Creativo Prim | C15: =VLOOKUP(B15,UNIFICADO!$C$5:$F$34,3,FALSE) -> 1 | D15: M2 | E15: =VLOOKUP(B15,UNIFICADO!$C$5:$F$34,2,FALSE) -> 90 | F15: =E15+30%*E15 -> 117 | H15: 1084.5763 | I15: =F15*H15 -> 126895.42
A16: 2.8 | B16: Taller Creativo Sec | C16: =VLOOKUP(B16,UNIFICADO!$C$5:$F$34,3,FALSE) -> 1 | D16: M2 | E16: =VLOOKUP(B16,UNIFICADO!$C$5:$F$34,2,FALSE) -> 90 | F16: =E16+30%*E16 -> 117 | H16: 1084.5763 | I16: =F16*H16 -> 126895.42
A17: 2.9 | B17: Taller EPT | C17: =VLOOKUP(B17,UNIFICADO!$C$5:$F$34,3,FALSE) -> 1 | D17: M2 | E17: =VLOOKUP(B17,UNIFICADO!$C$5:$F$34,2,FALSE) -> 90 | F17: =E17+30%*E17 -> 117 | H17: 1084.5763 | I17: =F17*H17 -> 126895.42
A18: 2.1 | B18: Laboratorio | C18: =VLOOKUP(B18,UNIFICADO!$C$5:$F$34,3,FALSE) -> 1 | D18: M2 | E18: =VLOOKUP(B18,UNIFICADO!$C$5:$F$34,2,FALSE) -> 90 | F18: =E18+30%*E18 -> 117 | H18: 1084.5763 | I18: =F18*H18 -> 126895.42
A19: 2.11 | B19: Área de Espera | C19: =VLOOKUP(B19,UNIFICADO!$C$5:$F$34,3,FALSE) -> 1 | D19: M2 | E19: =VLOOKUP(B19,UNIFICADO!$C$5:$F$34,2,FALSE) -> 15 | F19: =E19+30%*E19 -> 19.5 | H19: 1084.5763 | I19: =F19*H19 -> 21149.237
A20: 3 | B20: MODULO III | G20: =SUM(F21:F29) -> #DIV/0! | J20: =SUM(I21:I29) -> #DIV/0!
A21: 3.1 | B21: SSHH Inicial | C21: =VLOOKUP(B21,UNIFICADO!$C$5:$F$34,3,FALSE) -> 1 | D21: M2 | E21: =VLOOKUP(B21,UNIFICADO!$C$5:$F$34,2,FALSE) -> 0 | F21: =E21+30%*E21 -> 0 | H21: 1084.5763 | I21: =F21*H21 -> 0
A22: 3.2 | B22: SSHH Prim | C22: =VLOOKUP(B22,UNIFICADO!$C$5:$F$34,3,FALSE) -> 1 | D22: M2 | E22: =VLOOKUP(B22,UNIFICADO!$C$5:$F$34,2,FALSE) -> 35 | F22: =E22+30%*E22 -> 45.5 | H22: 1084.5763 | I22: =F22*H22 -> 49348.22
A23: 3.3 | B23: SSHH Sec | C23: =VLOOKUP(B23,UNIFICADO!$C$5:$F$34,3,FALSE) -> 1 | D23: M2 | E23: =VLOOKUP(B23,UNIFICADO!$C$5:$F$34,2,FALSE) -> 21.5 | F23: =E23+30%*E23 -> 27.95 | H23: 1084.5763 | I23: =F23*H23 -> 30313.907
A24: 3.4 | B24: SSHH Adm. | C24: =VLOOKUP(B24,UNIFICADO!$C$5:$F$34,3,FALSE) -> 1 | D24: M2 | E24: =VLOOKUP(B24,UNIFICADO!$C$5:$F$34,2,FALSE) -> #DIV/0! | F24: =E24+30%*E24 -> #DIV/0! | H24: 1084.5763 | I24: =F24*H24 -> #DIV/0!
A25: 3.5 | B25: Topico | C25: =VLOOKUP(B25,UNIFICADO!$C$5:$F$34,3,FALSE) -> 1 | D25: M2 | E25: =VLOOKUP(B25,UNIFICADO!$C$5:$F$34,2,FALSE) -> 27 | F25: =E25+30%*E25 -> 35.1 | H25: 1084.5763 | I25: =F25*H25 -> 38068.627
A26: 3.6 | B26: Lactario | C26: =VLOOKUP(B26,UNIFICADO!$C$5:$F$34,3,FALSE) -> 1 | D26: M2 | E26: =VLOOKUP(B26,UNIFICADO!$C$5:$F$34,2,FALSE) -> 22.5 | F26: =E26+30%*E26 -> 29.25 | H26: 1084.5763 | I26: =F26*H26 -> 31723.856
A27: 3.7 | B27: Cocina Prim - Sec | C27: =VLOOKUP(B27,UNIFICADO!$C$5:$F$34,3,FALSE) -> 1 | D27: M2 | E27: =VLOOKUP(B27,UNIFICADO!$C$5:$F$34,2,FALSE) -> 36.4 | F27: =E27+30%*E27 -> 47.32 | H27: 1084.5763 | I27: =F27*H27 -> 51322.149
A28: 3.8 | B28: Cocina Inicial | C28: =VLOOKUP(B28,UNIFICADO!$C$5:$F$34,3,FALSE) -> 1 | D28: M2 | E28: =VLOOKUP(B28,UNIFICADO!$C$5:$F$34,2,FALSE) -> 18.2 | F28: =E28+30%*E28 -> 23.66 | H28: 1084.5763 | I28: =F28*H28 -> 25661.075
A29: 3.9 | B29: Almacén | D29: M2
A30: 4 | B30: MODULO IV | G30: =SUM(F31:F36) -> 1632.15 | J30: =SUM(I31:I36) -> 1770191.2
A31: 4.1 | B31: SUM | C31: =VLOOKUP(B31,UNIFICADO!$C$5:$F$34,3,FALSE) -> 1 | D31: M2 | E31: =VLOOKUP(B31,UNIFICADO!$C$5:$F$34,2,FALSE) -> 172.5 | F31: =E31+30%*E31 -> 224.25 | H31: 1084.5763 | I31: =F31*H31 -> 243216.23
A32: 4.2 | B32: Losa Deportiva | C32: =VLOOKUP(B32,UNIFICADO!$C$5:$F$34,3,FALSE) -> 1 | D32: M2 | E32: =VLOOKUP(B32,UNIFICADO!$C$5:$F$34,2,FALSE) -> 840 | F32: =E32+30%*E32 -> 1092 | H32: 1084.5763 | I32: =F32*H32 -> 1184357.3
A33: 4.3 | B33: Patio de Inicial | C33: =VLOOKUP(B33,UNIFICADO!$C$5:$F$34,3,FALSE) -> 1 | D33: M2 | E33: =VLOOKUP(B33,UNIFICADO!$C$5:$F$34,2,FALSE) -> 150 | F33: =E33+30%*E33 -> 195 | H33: 1084.5763 | I33: =F33*H33 -> 211492.37
A34: 4.4 | B34: Escalera Prim | C34: =VLOOKUP(B34,UNIFICADO!$C$5:$F$34,3,FALSE) -> 2 | D34: M2 | E34: =VLOOKUP(B34,UNIFICADO!$C$5:$F$34,2,FALSE) -> 37.5 | F34: =E34+30%*E34 -> 48.75 | H34: 1084.5763 | I34: =F34*H34 -> 52873.093
A35: 4.5 | B35: Escalera Sec | C35: =VLOOKUP(B35,UNIFICADO!$C$5:$F$34,3,FALSE) -> 2 | D35: M2 | E35: =VLOOKUP(B35,UNIFICADO!$C$5:$F$34,2,FALSE) -> 37.5 | F35: =E35+30%*E35 -> 48.75 | H35: 1084.5763 | I35: =F35*H35 -> 52873.093
A36: 4.6 | B36: Area de Ingreso | C36: =VLOOKUP(B36,UNIFICADO!$C$5:$F$34,3,FALSE) -> 1 | D36: M2 | E36: =VLOOKUP(B36,UNIFICADO!$C$5:$F$34,2,FALSE) -> 18 | F36: =E36+30%*E36 -> 23.4 | H36: 1084.5763 | I36: =F36*H36 -> 25379.085
B37: COSTO DIRECTO | J37: =SUM(J2:J36) -> #DIV/0!
B38: GASTOS GENERALES (10%) | J38: =0.1*J37 -> #DIV/0!
B39: UTILIDAD (10%) | J39: =0.1*J37 -> #DIV/0!
B40: SUB TOTAL | J40: =J37+J38+J39 -> #DIV/0!
B41: IGV | J41: =0.18*J40 -> #DIV/0!
B42: PRESUPUESTO TOTAL | J42: =J40+J41 -> #DIV/0!
